wrestful/__init__.py
wrestful-0.0.0.dist-info/DESCRIPTION.rst
wrestful-0.0.0.dist-info/METADATA
wrestful-0.0.0.dist-info/RECORD
wrestful-0.0.0.dist-info/WHEEL
wrestful-0.0.0.dist-info/metadata.json
wrestful-0.0.0.dist-info/top_level.txt
