Metadata-Version: 2.0
Name: wrestful
Version: 0.0.0
Summary: A variant of restful
Home-page: https://github.com/claydodo/wrestful
Author: claydodo and his little friends (xiao huo ban)
Author-email: claydodo@foxmail.com
License: UNKNOWN
Platform: UNKNOWN
Classifier: Programming Language :: Python :: 2.7
Classifier: Framework :: Django
Classifier: Operating System :: OS Independent
